{
  "//": "See docs/FIRESTORE_CONFIG_VERIFICATION.md for details on required indexes.",
  "indexes": [
    {
      "collectionId": "books",
      "fields": [
        { "fieldPath": "userId", "order": "ASCENDING" },
        { "fieldPath": "createdAt", "order": "DESCENDING" }
      ]
    },
    {
      "collectionId": "templates",
      "fields": [
        { "fieldPath": "active", "order": "ASCENDING" },
        { "fieldPath": "order", "order": "ASCENDING" }
      ]
    },
    {
      "collectionId": "categoryGroups",
      "fields": [
        { "fieldPath": "active", "order": "ASCENDING" },
        { "fieldPath": "order", "order": "ASCENDING" }
      ]
    },
    {
      "collectionId": "companions",
      "fields": [
        { "fieldPath": "userId", "order": "ASCENDING" },
        { "fieldPath": "createdAt", "order": "DESCENDING" }
      ]
    },
    {
      "collectionId": "qualityTasks",
      "fields": [
        { "fieldPath": "status", "order": "ASCENDING" },
        { "fieldPath": "createdAtMs", "order": "DESCENDING" }
      ]
    },
    {
      "collectionId": "books",
      "fields": [
        { "fieldPath": "public", "order": "ASCENDING" },
        { "fieldPath": "createdAt", "order": "DESCENDING" }
      ]
    },
    {
      "collectionId": "series",
      "fields": [
        { "fieldPath": "userId", "order": "ASCENDING" },
        { "fieldPath": "createdAt", "order": "DESCENDING" }
      ]
    }
  ],
  "fieldOverrides": [
    {
      "//": "Required for cleanupStaleGeneration collection group query.",
      "collectionGroup": "pages",
      "fieldPath": "status",
      "indexes": [
        {
          "order": "ASCENDING",
          "queryScope": "COLLECTION_GROUP"
        }
      ]
    }
  ]
}
